glcl/__init__.py
glcl/__init__.pyi
glcl/__version__.py
glcl/Win32/glcl.pyd
glcl/Win64/glcl.pyd
glcl/doc/docs.xml
glcl-0.3.1.dist-info/METADATA
glcl-0.3.1.dist-info/WHEEL
glcl-0.3.1.dist-info/top_level.txt
glcl-0.3.1.dist-info/RECORD
